redcamel/__init__.py
redcamel/icon.png
redcamel/remi_calculator.py
redcamel/remi_gui.py
redcamel/remi_particles.py
redcamel/units.py
redcamel-0.1.7.dist-info/licenses/CITATION.cff
redcamel-0.1.7.dist-info/licenses/LICENSES/CC-BY-4.0.txt
redcamel-0.1.7.dist-info/licenses/LICENSES/CC0-1.0.txt
redcamel-0.1.7.dist-info/licenses/LICENSES/GPL-3.0-or-later.txt
redcamel-0.1.7.dist-info/licenses/REUSE.toml
redcamel-0.1.7.dist-info/WHEEL
redcamel-0.1.7.dist-info/entry_points.txt
redcamel-0.1.7.dist-info/METADATA
redcamel-0.1.7.dist-info/RECORD
