Metadata-Version: 2.4
Name: redcamel
Version: 0.1.7
Summary: GUI tool to simulate Reaction Microscope detector images.
Author: Patrizia Schoch, Hannes Lindenblatt, Magdalena Orlowska
Author-email: Hannes Lindenblatt <hannes.lindenblatt@desy.de>
License-Expression: GPL-3.0-or-later
License-File: CITATION.cff
License-File: LICENSES/CC-BY-4.0.txt
License-File: LICENSES/CC0-1.0.txt
License-File: LICENSES/GPL-3.0-or-later.txt
License-File: REUSE.toml
Classifier: Programming Language :: Python :: 3
Classifier: Operating System :: OS Independent
Classifier: Development Status :: 3 - Alpha
Classifier: License :: OSI Approved :: GNU General Public License v3 or later (GPLv3+)
Classifier: Intended Audience :: Science/Research
Classifier: Topic :: Scientific/Engineering :: Physics
Classifier: Topic :: Scientific/Engineering :: Visualization
Requires-Dist: chemformula>=1.2
Requires-Dist: graphviz>=0.20
Requires-Dist: h5py>=3.11
Requires-Dist: ipywidgets>=8
Requires-Dist: ipympl>=0.9
Requires-Dist: matplotlib>=3.7
Requires-Dist: numba>=0.58
Requires-Dist: numpy>=1.2
Requires-Dist: plopp>=23
Requires-Dist: scipp>=23
Requires-Dist: scipy>=1.10
Maintainer: Hannes Lindenblatt
Maintainer-email: Hannes Lindenblatt <hannes.lindenblatt@desy.de>
Requires-Python: >=3.8
Project-URL: Homepage, https://codeberg.org/FlashREMI/RedCamel
Project-URL: Repository, https://codeberg.org/FlashREMI/RedCamel.git
